authing/AuthenticationClient.py
authing/AuthingException.py
authing/ManagementClient.py
authing/ManagementTokenProvider.py
authing/__init__.py
authing/constants.py
authing/exceptions.py
authing/version.py
authing/http/AuthenticationHttpClient.py
authing/http/ManagementHttpClient.py
authing/http/ProtocolHttpClient.py
authing/http/__init__.py
authing/utils/__init__.py
authing/utils/signatureComposer.py
authing/utils/wss.py
authing-5.1.0.dist-info/LICENSE
authing-5.1.0.dist-info/METADATA
authing-5.1.0.dist-info/WHEEL
authing-5.1.0.dist-info/top_level.txt
authing-5.1.0.dist-info/RECORD
